gencode/main.py
gencode/version.py
gencode/common/__init__.py
gencode/common/config.py
gencode/common/data.py
gencode/common/db.py
gencode/common/models.py
gencode/common/sqls.py
gencode/common/utils.py
genCode-1.0.1.dist-info/LICENSE
genCode-1.0.1.dist-info/METADATA
genCode-1.0.1.dist-info/WHEEL
genCode-1.0.1.dist-info/entry_points.txt
genCode-1.0.1.dist-info/top_level.txt
genCode-1.0.1.dist-info/RECORD
