Metadata-Version: 2.1
Name: genCode
Version: 1.0.1
Summary: 生成代码
Author: hammer
Author-email: liuzhuogood@foxmail.com
License-File: LICENSE
Requires-Dist: db-hammer
Requires-Dist: PyMySQL
Requires-Dist: cx-Oracle
Requires-Dist: click
Requires-Dist: jinja2
Requires-Dist: PyYAML
